tune_vera-0.0.1.dist-info/licenses/LICENSE
tunevera/__init__.py
tunevera/adapter.py
tunevera/data.py
tunevera/embedding.py
tunevera/index.py
tunevera/llm.py
tunevera/py.typed
tune_vera-0.0.1.dist-info/METADATA
tune_vera-0.0.1.dist-info/WHEEL
tune_vera-0.0.1.dist-info/top_level.txt
tune_vera-0.0.1.dist-info/RECORD
