Metadata-Version: 2.4
Name: tune-vera
Version: 0.0.1
Summary: Vector Embedding Retrieval Adaptation
Author-email: Angelo Castillo <castillomeca53@gmail.com>
License-Expression: MIT
Project-URL: Homepage, https://github.com/AngeloCastillo/vera
Classifier: Programming Language :: Python :: 3
Classifier: Operating System :: OS Independent
Requires-Python: >=3.7
License-File: LICENSE
Dynamic: license-file
